[{"name":"initializing","time":1417857.395},{"name":"configuration_loaded","time":1426581.616},{"name":"start_exercise","time":741170.367,"data":"00-welcome"},{"name":"start_exercise","time":847420.964,"data":"01-installing-node"},{"name":"start_exercise","time":998079.017,"data":"02-installing-express"},{"name":"start_exercise","time":1452053.025,"data":"03-first-express-app"},{"name":"start_exercise","time":1075977.459,"data":"00-welcome"},{"name":"start_exercise","time":1439523.456,"data":"01-installing-node"},{"name":"start_exercise","time":858753.738,"data":"02-installing-express"},{"name":"start_exercise","time":1458356.058,"data":"03-first-express-app"},{"name":"start_exercise","time":1083314.441,"data":"04-run-your-app"},{"name":"start_exercise","time":1225261.889,"data":"03-first-express-app"},{"name":"start_exercise","time":1351612.305,"data":"04-run-your-app"},{"name":"start_exercise","time":1028943.648,"data":"05-your-first-route"},{"name":"start_exercise","time":1486332.065,"data":"04-run-your-app"},{"name":"start_exercise","time":1907649.406,"data":"05-your-first-route"},{"name":"start_exercise","time":1459842.372,"data":"06-returning-json"},{"name":"start_exercise","time":1929604.944,"data":"07-post-todo"},{"name":"start_exercise","time":1825846.24,"data":"00-welcome"},{"name":"start_exercise","time":1972983.947,"data":"07-post-todo"},{"name":"start_exercise","time":1784381.54,"data":"06-returning-json"},{"name":"start_exercise","time":2053259.206,"data":"05-your-first-route"},{"name":"start_exercise","time":1875801.657,"data":"06-returning-json"},{"name":"start_exercise","time":1726881.956,"data":"07-post-todo"},{"name":"open_window","time":1462210.707,"data":{"url":"https://www.postman.com/","exerciseSlug":"07-post-todo"}},{"name":"start_exercise","time":2281839.751,"data":"07.1-check-post-todo"},{"name":"start_exercise","time":1970752.862,"data":"07-post-todo"},{"name":"start_exercise","time":2356561.448,"data":"06-returning-json"},{"name":"start_exercise","time":2499113.607,"data":"00-welcome"},{"name":"start_exercise","time":1866715.671,"data":"01-installing-node"},{"name":"start_exercise","time":2089161.604,"data":"02-installing-express"},{"name":"start_exercise","time":2496758.894,"data":"03-first-express-app"},{"name":"start_exercise","time":2104638.655,"data":"04-run-your-app"},{"name":"start_exercise","time":1974653.955,"data":"05-your-first-route"},{"name":"start_exercise","time":1965213.223,"data":"06-returning-json"},{"name":"start_exercise","time":2690482.577,"data":"07-post-todo"},{"name":"start_exercise","time":2734012.616,"data":"07.1-check-post-todo"},{"name":"start_exercise","time":2640613.425,"data":"08-delete-todo"},{"name":"start_exercise","time":2613350.355,"data":"07.1-check-post-todo"},{"name":"start_exercise","time":3138616.527,"data":"07-post-todo"},{"name":"start_exercise","time":2454918.901,"data":"06-returning-json"},{"name":"start_exercise","time":2842651.167,"data":"07-post-todo"},{"name":"start_exercise","time":3015659.147,"data":"06-returning-json"},{"name":"start_exercise","time":2653476.131,"data":"07-post-todo"},{"name":"start_exercise","time":3139942.09,"data":"00-welcome"},{"name":"start_exercise","time":2501879.347,"data":"01-installing-node"},{"name":"start_exercise","time":2554973.341,"data":"02-installing-express"},{"name":"start_exercise","time":2678016.27,"data":"03-first-express-app"},{"name":"start_exercise","time":2972067.782,"data":"04-run-your-app"},{"name":"start_exercise","time":2399604.424,"data":"05-your-first-route"},{"name":"start_exercise","time":2652979.272,"data":"06-returning-json"},{"name":"start_exercise","time":3093227.475,"data":"07-post-todo"},{"name":"start_exercise","time":2558492.046,"data":"07.1-check-post-todo"},{"name":"start_exercise","time":3284459.972,"data":"08-delete-todo"},{"name":"start_exercise","time":2768448.74,"data":"08.1-check-delete-todo"}]